buildtools4py/__init__.py
buildtools4py/apksigner.py
buildtools4py-0.1.6.dist-info/LICENSES/Apache-2.0.txt
buildtools4py-0.1.6.dist-info/LICENSES/CC0-1.0.txt
buildtools4py-0.1.6.dist-info/METADATA
buildtools4py-0.1.6.dist-info/WHEEL
buildtools4py-0.1.6.dist-info/RECORD
