Metadata-Version: 2.1
Name: buildtools4py
Version: 0.1.6
Summary: python wrapper for (some) Android build-tools
Home-page: https://codeberg.org/uniqx/buildtools4py
License: Apache-2.0
Author: Michael Pöhn
Author-email: michael@poehn.at
Requires-Python: >=3.7,<4.0
Classifier: License :: OSI Approved :: Apache Software License
Classifier: Programming Language :: Python :: 3
Classifier: Programming Language :: Python :: 3.7
Classifier: Programming Language :: Python :: 3.8
Classifier: Programming Language :: Python :: 3.9
Classifier: Programming Language :: Python :: 3.10
Classifier: Programming Language :: Python :: 3.11
